{
  "publicPath": "https://file.calibur.tv/web/",
  "all": [
    "../server/index.spa.html",
    "../server/index.ssr.html",
    "01d0e628f2e2fd99d34b.css",
    "01ef1929339ced88b360.js",
    "068e31b9cfb2a1f323c7.js",
    "069296e6a91f32f2a33c.css",
    "09fcce816da279344f0f.js",
    "0e4338761429b4eb16ac.css",
    "147a7fa5f3d1d2aa630b.js",
    "16c58ba7113d66f0429d.css",
    "1dfd7eba873dea5d2099.js",
    "26e3844b218c0b5e2e5f.js",
    "282e57ef9125d67847fa.css",
    "2cf8177f2bc0cc0607d8.js",
    "361904d513e233a610ec.js",
    "367c3ec980f82a4a0703.js",
    "3757f229453f330a74ee.js",
    "38082ef60047c29d57cd.js",
    "41124400a83eb525bf08.css",
    "48a2df7cea1b8422d699.js",
    "49119de98847fb151006.js",
    "49e762b335e6e483107b.js",
    "4f66673c19b373a61d8a.css",
    "5012b29cb453a94445d9.css",
    "63fd95d42884f282086f.js",
    "6c93c987ff832d5d8921.js",
    "6f6bfe4dc68f4249ef0c.js",
    "7024de4a9152cc8cf4bf.css",
    "772da461fb9d6e5b0200.js",
    "77ee8e3ad8ede9b1cf74.css",
    "7a2e040ed89501ffa278.js",
    "837e5ccff1f84dc31e5c.js",
    "85e1ca3911df2e9d11c9.js",
    "874327057dbddee5787d.js",
    "8e95980befef01b638d9.js",
    "95c654dbab91e9b317ca.css",
    "9c56fe982d45ba18523f.css",
    "9c5d8c305eae84115714.js",
    "9db1a4e1154f3613e41c.css",
    "9e0b6c68552ec9afc1a8.css",
    "LICENSES",
    "a338aaa5d928f106b53a.js",
    "af26153217755f751c5c.js",
    "afe15297bc91c3978485.js",
    "b13f2114018486ce6b61.js",
    "b79aa88aa31875cd5650.js",
    "bb062fa75d7c1914a441.js",
    "bb76858497b8401d8c1e.js",
    "c14f6a5fba3cc7c8ec95.js",
    "c69c67e5939fec6248d5.js",
    "c8ce325236157cc3e82a.css",
    "ccacb95a7a151e2a5eb1.js",
    "cf4bb06780e032e74477.js",
    "d00a54dd7f722d1efa47.js",
    "d0aebe7d6fb1619b2b80.js",
    "d0f3232ef7fd36707b2a.js",
    "d1b0fa53ff39c443e2f3.css",
    "dbdf9ab5b26845c01d05.css",
    "e1432ec96fd88320a590.js",
    "e266441b720a552c0d6f.css",
    "e461e4e64a928cf0eadd.js",
    "e6e6152e56c550d24498.js",
    "e792f7b476c091f672dd.js",
    "e94f3b72cdd433482cce.js",
    "ee9ee360b140ce490d48.js",
    "f2292a5257ba28ae6145.css",
    "f3367608a86c2df881ce.css",
    "f428cd859141d5ae8175.js",
    "f43df91d429ecf845bb5.js",
    "fb23ebde330ca01479b0.css",
    "fonts/535877f.woff",
    "fonts/732389d.ttf",
    "img/adea640.jpeg",
    "img/b07f58f.jpeg",
    "img/d465ab1.jpeg",
    "img/e82d3e7.png",
    "manifest.8593452c.json"
  ],
  "initial": [
    "38082ef60047c29d57cd.js",
    "6f6bfe4dc68f4249ef0c.js",
    "9c56fe982d45ba18523f.css",
    "63fd95d42884f282086f.js",
    "4f66673c19b373a61d8a.css",
    "8e95980befef01b638d9.js"
  ],
  "async": [
    "01d0e628f2e2fd99d34b.css",
    "01ef1929339ced88b360.js",
    "068e31b9cfb2a1f323c7.js",
    "069296e6a91f32f2a33c.css",
    "09fcce816da279344f0f.js",
    "0e4338761429b4eb16ac.css",
    "147a7fa5f3d1d2aa630b.js",
    "16c58ba7113d66f0429d.css",
    "1dfd7eba873dea5d2099.js",
    "26e3844b218c0b5e2e5f.js",
    "282e57ef9125d67847fa.css",
    "2cf8177f2bc0cc0607d8.js",
    "361904d513e233a610ec.js",
    "367c3ec980f82a4a0703.js",
    "3757f229453f330a74ee.js",
    "41124400a83eb525bf08.css",
    "48a2df7cea1b8422d699.js",
    "49119de98847fb151006.js",
    "49e762b335e6e483107b.js",
    "5012b29cb453a94445d9.css",
    "6c93c987ff832d5d8921.js",
    "7024de4a9152cc8cf4bf.css",
    "772da461fb9d6e5b0200.js",
    "77ee8e3ad8ede9b1cf74.css",
    "7a2e040ed89501ffa278.js",
    "837e5ccff1f84dc31e5c.js",
    "85e1ca3911df2e9d11c9.js",
    "874327057dbddee5787d.js",
    "95c654dbab91e9b317ca.css",
    "9c5d8c305eae84115714.js",
    "9db1a4e1154f3613e41c.css",
    "9e0b6c68552ec9afc1a8.css",
    "a338aaa5d928f106b53a.js",
    "af26153217755f751c5c.js",
    "afe15297bc91c3978485.js",
    "b13f2114018486ce6b61.js",
    "b79aa88aa31875cd5650.js",
    "bb062fa75d7c1914a441.js",
    "bb76858497b8401d8c1e.js",
    "c14f6a5fba3cc7c8ec95.js",
    "c69c67e5939fec6248d5.js",
    "c8ce325236157cc3e82a.css",
    "ccacb95a7a151e2a5eb1.js",
    "cf4bb06780e032e74477.js",
    "d00a54dd7f722d1efa47.js",
    "d0aebe7d6fb1619b2b80.js",
    "d0f3232ef7fd36707b2a.js",
    "d1b0fa53ff39c443e2f3.css",
    "dbdf9ab5b26845c01d05.css",
    "e1432ec96fd88320a590.js",
    "e266441b720a552c0d6f.css",
    "e461e4e64a928cf0eadd.js",
    "e6e6152e56c550d24498.js",
    "e792f7b476c091f672dd.js",
    "e94f3b72cdd433482cce.js",
    "ee9ee360b140ce490d48.js",
    "f2292a5257ba28ae6145.css",
    "f3367608a86c2df881ce.css",
    "f428cd859141d5ae8175.js",
    "f43df91d429ecf845bb5.js",
    "fb23ebde330ca01479b0.css"
  ],
  "modules": {
    "12343270": [
      9,
      20
    ],
    "12410842": [
      36,
      24
    ],
    "19743845": [
      3
    ],
    "19802179": [
      26
    ],
    "29751858": [
      21
    ],
    "32073284": [
      29,
      46
    ],
    "32187542": [
      26
    ],
    "36026624": [
      56,
      45
    ],
    "46774040": [
      39,
      68
    ],
    "54806245": [
      22,
      34,
      73,
      74,
      72,
      70,
      71
    ],
    "56807672": [
      26
    ],
    "57155158": [
      38,
      64,
      75
    ],
    "62248782": [
      59,
      13
    ],
    "69186058": [
      26
    ],
    "79985926": [
      5,
      60
    ],
    "93746146": [
      7,
      10
    ],
    "779517e2": [
      26
    ],
    "58ca916c": [
      22,
      34,
      73,
      74,
      72,
      70,
      71
    ],
    "bb10628e": [
      26
    ],
    "088e4043": [
      26
    ],
    "4a243cc9": [
      26
    ],
    "5a95297a": [
      26
    ],
    "eacaa546": [
      26
    ],
    "0363445e": [
      26
    ],
    "1db6a7a4": [
      36,
      24
    ],
    "7ac0edc9": [
      26
    ],
    "4c31e718": [
      26
    ],
    "c8cfbff8": [
      26
    ],
    "19694ccd": [
      26
    ],
    "7037d730": [
      26
    ],
    "2d206cc4": [
      26
    ],
    "0e8bd800": [
      26
    ],
    "3cbfeee3": [
      26
    ],
    "0d6740f6": [
      26
    ],
    "28d147ec": [
      26
    ],
    "23cadee6": [
      26
    ],
    "5aaf169d": [
      26
    ],
    "232eb830": [
      26
    ],
    "6e7b6f0a": [
      26
    ],
    "657c3a94": [
      26
    ],
    "73c354b4": [
      22,
      34,
      73,
      74,
      72,
      70,
      71
    ],
    "269e1d54": [
      36,
      24
    ],
    "a282c0ee": [
      22,
      34,
      73,
      74,
      72,
      70,
      71
    ],
    "63534eea": [
      22,
      34,
      73,
      74,
      72,
      70,
      71
    ],
    "63edbbc8": [
      22,
      34,
      73,
      74,
      72,
      70,
      71
    ],
    "c602f160": [
      22,
      34,
      73,
      74,
      72,
      70,
      71
    ],
    "acdb5c8e": [
      22,
      34,
      73,
      74,
      72,
      70,
      71
    ],
    "c988d682": [
      22,
      34,
      73,
      74,
      72,
      70,
      71
    ],
    "3cc5c60c": [
      22,
      34,
      73,
      74,
      72,
      70,
      71
    ],
    "0e63a11a": [
      22,
      34,
      73,
      74,
      72,
      70,
      71
    ],
    "98bbcd7e": [
      22,
      34,
      73,
      74,
      72,
      70,
      71
    ],
    "ec732d36": [
      22,
      34,
      73,
      74,
      72,
      70,
      71
    ],
    "1f010a43": [
      22,
      34,
      73,
      74,
      72,
      70,
      71
    ],
    "2ab66299": [
      22,
      34,
      73,
      74,
      72,
      70,
      71
    ],
    "2bd275be": [
      22,
      34,
      73,
      74,
      72,
      70,
      71
    ],
    "ef43e778": [
      22,
      34,
      73,
      74,
      72,
      70,
      71
    ],
    "7dba2380": [
      22,
      34,
      73,
      74,
      72,
      70,
      71
    ],
    "7c5f6d26": [
      22,
      34,
      73,
      74,
      72,
      70,
      71
    ],
    "f0b1e7b4": [
      22,
      34,
      73,
      74,
      72,
      70,
      71
    ],
    "7f019f08": [
      22,
      34,
      73,
      74,
      72,
      70,
      71
    ],
    "3f4e7c32": [
      22,
      34,
      73,
      74,
      72,
      70,
      71
    ],
    "71d32686": [
      22,
      34,
      73,
      74,
      72,
      70,
      71
    ],
    "603ac224": [
      22,
      34,
      73,
      74,
      72,
      70,
      71
    ],
    "048f1669": [
      22,
      34,
      73,
      74,
      72,
      70,
      71
    ],
    "58184d28": [
      22,
      34,
      73,
      74,
      72,
      70,
      71
    ],
    "00b9f7a7": [
      22,
      34,
      73,
      74,
      72,
      70,
      71
    ],
    "364418b0": [
      22,
      34,
      73,
      74,
      72,
      70,
      71
    ],
    "487a5470": [
      22,
      34,
      73,
      74,
      72,
      70,
      71
    ],
    "867b9fd8": [
      22,
      34,
      73,
      74,
      72,
      70,
      71
    ],
    "d7f355b0": [
      22,
      34,
      73,
      74,
      72,
      70,
      71
    ],
    "38d7ffd7": [
      22,
      34,
      73,
      74,
      72,
      70,
      71
    ],
    "59910e9c": [
      22,
      34,
      73,
      74,
      72,
      70,
      71
    ],
    "0efcf90e": [
      22,
      34,
      73,
      74,
      72,
      70,
      71
    ],
    "1763ada8": [
      22,
      34,
      73,
      74,
      72,
      70,
      71
    ],
    "5eb397cc": [
      22,
      34,
      73,
      74,
      72,
      70,
      71
    ],
    "8bb9eb50": [
      22,
      34,
      73,
      74,
      72,
      70,
      71
    ],
    "7d03064e": [
      22,
      34,
      73,
      74,
      72,
      70,
      71
    ],
    "e9b39a92": [
      26
    ],
    "7a0ea517": [
      26
    ],
    "1e25dece": [
      26
    ],
    "32c06df0": [
      26
    ],
    "4c8c570a": [
      26
    ],
    "5749613c": [
      26
    ],
    "7a4a2280": [
      26
    ],
    "4d9a2514": [
      26
    ],
    "56f69ade": [
      26
    ],
    "53c20bd8": [
      26
    ],
    "db56856c": [
      26
    ],
    "7fa1d6ef": [
      26
    ],
    "6d1b4930": [
      26
    ],
    "0c6d37de": [
      26
    ],
    "08ced7e3": [
      22,
      34,
      73,
      74,
      72,
      70,
      71
    ],
    "3b960d7d": [
      36,
      24
    ],
    "e46d1540": [
      26
    ],
    "0b6f74a7": [
      26
    ],
    "05018e72": [
      26
    ],
    "3223258a": [
      26
    ],
    "757d589d": [
      26
    ],
    "5979cf61": [
      26
    ],
    "06f4f9ac": [
      26
    ],
    "19f1e879": [
      26
    ],
    "2b031a28": [
      36,
      24
    ],
    "cb96208a": [
      36,
      24
    ],
    "9e3cd966": [
      26
    ],
    "b27d3cfe": [
      26
    ],
    "79afa3f4": [
      26
    ],
    "58214c74": [
      26
    ],
    "50ce3ec6": [
      36,
      24
    ],
    "3e63f6e8": [
      26
    ],
    "4e9c6037": [
      36,
      24
    ],
    "0a4fceab": [
      26
    ],
    "f92b919e": [
      22,
      34,
      73,
      74,
      72,
      70,
      71
    ],
    "3d8efad9": [
      26
    ],
    "30f2831d": [
      26
    ],
    "1d312793": [
      26
    ],
    "9327ade6": [
      36,
      24
    ],
    "9fc28af0": [
      26
    ],
    "48ce1a0e": [
      26
    ],
    "b028e79c": [
      26
    ],
    "7664c56f": [
      26
    ],
    "51609e1b": [
      26
    ],
    "3e1f5e22": [
      26
    ],
    "43472a85": [
      26
    ],
    "2df3196c": [
      26
    ],
    "0c3fd553": [
      26
    ],
    "7c15251e": [
      26
    ],
    "01efe9e2": [
      26
    ],
    "4f22c808": [
      22,
      34,
      73,
      74,
      72,
      70,
      71
    ],
    "608662fd": [
      22,
      34,
      73,
      74,
      72,
      70,
      71
    ],
    "9bc80336": [
      36,
      24
    ],
    "7da7a5ef": [
      22,
      34,
      73,
      74,
      72,
      70,
      71
    ],
    "174ef3b0": [
      36,
      24
    ],
    "7d28378a": [
      36,
      24
    ],
    "3f0e9ac6": [
      36,
      24
    ],
    "3080f81c": [
      36,
      24
    ],
    "64a09d8d": [
      22,
      34,
      73,
      74,
      72,
      70,
      71
    ],
    "02ba9a4e": [
      26
    ],
    "005d42e4": [
      26
    ],
    "68f9c152": [
      26
    ],
    "ca22a09a": [
      36,
      24
    ],
    "1700b03f": [
      26
    ],
    "6536518c": [
      26
    ],
    "d05f13b4": [
      36,
      24
    ],
    "28ae3939": [
      26
    ],
    "656c7f85": [
      26
    ],
    "0319cf16": [
      26
    ],
    "bcffa92e": [
      26
    ],
    "9c0c960a": [
      26
    ],
    "d1e42636": [
      26
    ],
    "0058b72e": [
      26
    ],
    "630be76b": [
      26
    ],
    "907ae266": [
      26
    ],
    "6be54f04": [
      26
    ],
    "4f9e51f6": [
      26
    ],
    "4dcfbc34": [
      36,
      24
    ],
    "5cbcc0ec": [
      26
    ],
    "791f6baa": [
      26
    ],
    "1c851d76": [
      26
    ],
    "46eb4534": [
      26
    ],
    "90d62f6e": [
      26
    ],
    "356ac2ca": [
      26
    ],
    "b18f49d6": [
      26
    ],
    "6aebcf15": [
      26
    ],
    "080449bd": [
      26
    ],
    "f88f836e": [
      26
    ],
    "3a72fcc9": [
      26
    ],
    "5efc3b9b": [
      26
    ],
    "7e29fe52": [
      26
    ],
    "ecdd9186": [
      36,
      24
    ],
    "ad8d23fe": [
      22,
      34,
      73,
      74,
      72,
      70,
      71
    ],
    "393f56b8": [
      26
    ],
    "e52f0a98": [
      26
    ],
    "0156688f": [
      36,
      24
    ],
    "193fb11b": [
      36,
      24
    ],
    "46cde0da": [
      36,
      24
    ],
    "6d566397": [
      36,
      24
    ],
    "f217d606": [
      36,
      24
    ],
    "5bc85497": [
      36,
      24
    ],
    "1a7efd11": [
      22,
      34,
      73,
      74,
      72,
      70,
      71
    ],
    "9e4e8b5a": [
      36,
      24
    ],
    "416d3910": [
      26
    ],
    "00665a50": [
      26
    ],
    "0c7a700e": [
      26
    ],
    "0d03c8da": [
      36,
      24
    ],
    "f1f14de8": [
      36,
      24
    ],
    "94f4d0c6": [
      22,
      34,
      73,
      74,
      72,
      70,
      71
    ],
    "06f99d5a": [
      26
    ],
    "1e649fa6": [
      26
    ],
    "47c8e83a": [
      26
    ],
    "47d9455e": [
      26
    ],
    "0e5ac0b4": [
      26
    ],
    "18eff6b3": [
      26
    ],
    "dd993c9c": [
      26
    ],
    "298aee75": [
      26
    ],
    "693d4d24": [
      26
    ],
    "0242a5fe": [
      26
    ],
    "07c93103": [
      26
    ],
    "5e2bdaef": [
      26
    ],
    "c34d1afa": [
      26
    ],
    "a526a3ae": [
      26
    ],
    "432bbf6e": [
      26
    ],
    "599178e7": [
      26
    ],
    "222e7f95": [
      26
    ],
    "30ec46c8": [
      26
    ],
    "a58a4010": [
      26
    ],
    "71f08c3a": [
      26
    ],
    "855644a0": [
      22,
      34,
      73,
      74,
      72,
      70,
      71
    ],
    "fe920d96": [
      22,
      34,
      73,
      74,
      72,
      70,
      71
    ],
    "7c25d1f4": [
      22,
      34,
      73,
      74,
      72,
      70,
      71
    ],
    "dcd2f50e": [
      26
    ],
    "00b2b8d6": [
      26
    ],
    "6c5b87d6": [
      26
    ],
    "19b95d64": [
      26
    ],
    "408911ee": [
      26
    ],
    "72ca4338": [
      26
    ],
    "7f1f5c76": [
      26
    ],
    "3b83ea7f": [
      26
    ],
    "4a4e976e": [
      26
    ],
    "1e8e4f59": [
      26
    ],
    "270c63f8": [
      26
    ],
    "07c9fe06": [
      26
    ],
    "5db35fb4": [
      26
    ],
    "0768e744": [
      26
    ],
    "02ab7e72": [
      26
    ],
    "35fcd9b8": [
      26
    ],
    "6ae9893a": [
      26
    ],
    "688a12ed": [
      36,
      24
    ],
    "399a5643": [
      26
    ],
    "600d0b1d": [
      26
    ],
    "2ccddc3c": [
      36,
      24
    ],
    "2ca33352": [
      26
    ],
    "924366f4": [
      36,
      24
    ],
    "11e2c7a0": [
      36,
      24
    ],
    "093ce05c": [
      26
    ],
    "465b1134": [
      26
    ],
    "5e1b7cbb": [
      36,
      24
    ],
    "fcb04ea2": [
      36,
      24
    ],
    "3b7485b6": [
      26
    ],
    "717562c0": [
      36,
      24
    ],
    "1e2b7434": [
      26
    ],
    "66d73926": [
      26
    ],
    "6ea31f4a": [
      26
    ],
    "3d25efec": [
      36,
      24
    ],
    "39d9acb4": [
      26
    ],
    "18a96e56": [
      26
    ],
    "c9054bda": [
      26
    ],
    "7c551589": [
      26
    ],
    "6e630bca": [
      26
    ],
    "313b659c": [
      36,
      24
    ],
    "12ffa376": [
      36,
      24
    ],
    "6433c1d4": [
      22,
      34,
      73,
      74,
      72,
      70,
      71
    ],
    "306ce9b0": [
      22,
      34,
      73,
      74,
      72,
      70,
      71
    ],
    "b1dde5c4": [
      26
    ],
    "0125c6d1": [
      26
    ],
    "34bcf453": [
      26
    ],
    "23ba6f32": [
      26
    ],
    "b25e488c": [
      26
    ],
    "7a279746": [
      26
    ],
    "0162101b": [
      26
    ],
    "2ea9ac81": [
      26
    ],
    "4d80e7f8": [
      26
    ],
    "6bd8e836": [
      26
    ],
    "3287bc11": [
      26
    ],
    "7f8a90a2": [
      26
    ],
    "475724ce": [
      26
    ],
    "b2ac2f7e": [
      26
    ],
    "6109b92e": [
      26
    ],
    "6ff10073": [
      26
    ],
    "102c9aa5": [
      26
    ],
    "1722d1e0": [
      26
    ],
    "5a086299": [
      26
    ],
    "0b78066a": [
      26
    ],
    "1179d05b": [
      26
    ],
    "006569c8": [
      26
    ],
    "0f6292a5": [
      26
    ],
    "3fe21338": [
      26
    ],
    "0879517c": [
      26
    ],
    "2ab260ce": [
      26
    ],
    "3585611c": [
      26
    ],
    "7b1930e6": [
      22,
      34,
      73,
      74,
      72,
      70,
      71
    ],
    "5c47134d": [
      22,
      34,
      73,
      74,
      72,
      70,
      71
    ],
    "d2c0f644": [
      22,
      34,
      73,
      74,
      72,
      70,
      71
    ],
    "0be417eb": [
      22,
      34,
      73,
      74,
      72,
      70,
      71
    ],
    "92b38d60": [
      36,
      24
    ],
    "5726ca44": [
      22,
      34,
      73,
      74,
      72,
      70,
      71
    ],
    "65545a81": [
      22,
      34,
      73,
      74,
      72,
      70,
      71
    ],
    "2ac46cd9": [
      22,
      34,
      73,
      74,
      72,
      70,
      71
    ],
    "4638b578": [
      36,
      24
    ],
    "fe21a2d6": [
      22,
      34,
      73,
      74,
      72,
      70,
      71
    ],
    "40c65f78": [
      26
    ],
    "2e1378ee": [
      26
    ],
    "ab13120c": [
      26
    ],
    "db5af2d4": [
      26
    ],
    "385d620a": [
      26
    ],
    "8d84f5cc": [
      26
    ],
    "d92a491a": [
      26
    ],
    "322202d3": [
      26
    ],
    "2cb436f8": [
      26
    ],
    "6ed9ada3": [
      26
    ],
    "fbb915b2": [
      26
    ],
    "3061386e": [
      26
    ],
    "2960704a": [
      26
    ],
    "074e5a95": [
      26
    ],
    "111cd9f6": [
      26
    ],
    "0dd768c3": [
      26
    ],
    "59b0a42c": [
      36,
      24
    ],
    "250ada04": [
      36,
      24
    ],
    "c3c54dc2": [
      26
    ],
    "04e4a147": [
      26
    ],
    "5e0203e7": [
      26
    ],
    "69408a5c": [
      26
    ],
    "15e4ca51": [
      26
    ],
    "bbc913fe": [
      26
    ],
    "5ac73cb6": [
      26
    ],
    "27abede0": [
      26
    ],
    "7b26be78": [
      36,
      24
    ],
    "e39eff4e": [
      26
    ],
    "1f615b7a": [
      26
    ],
    "272adc5f": [
      26
    ],
    "6c3df17d": [
      26
    ],
    "244277b2": [
      26
    ],
    "6a3debd5": [
      26
    ],
    "1a0906f0": [
      26
    ],
    "fa8a7952": [
      26
    ],
    "514961e6": [
      26
    ],
    "762fa352": [
      26
    ],
    "3ce4922d": [
      26
    ],
    "1c4d660e": [
      36,
      24
    ],
    "75baa455": [
      26
    ],
    "b56e5ade": [
      26
    ],
    "5982073b": [
      26
    ],
    "40535aee": [
      26
    ],
    "31e5232a": [
      26
    ],
    "1f3bd066": [
      26
    ],
    "6ae4fd84": [
      26
    ],
    "2609ac75": [
      26
    ],
    "31f941cf": [
      26
    ],
    "63d9722b": [
      26
    ],
    "150a4b84": [
      36,
      24
    ],
    "f84f5132": [
      36,
      24
    ],
    "0ce77509": [
      36,
      24
    ],
    "e28cc99e": [
      36,
      24
    ],
    "7962a9ff": [
      36,
      24
    ],
    "46a9b09d": [
      36,
      24
    ],
    "2d098979": [
      36,
      24
    ],
    "5def8b46": [
      36,
      24
    ],
    "2fa2084b": [
      36,
      24
    ],
    "710e9029": [
      36,
      24
    ],
    "5becd664": [
      36,
      24
    ],
    "0c689856": [
      36,
      24
    ],
    "1ade147e": [
      36,
      24
    ],
    "29a8d24c": [
      36,
      24
    ],
    "f7103c2c": [
      36,
      24
    ],
    "5ccfff1a": [
      36,
      24
    ],
    "1bd0089c": [
      36,
      24
    ],
    "43c8e3ab": [
      36,
      24
    ],
    "e44a341c": [
      36,
      24
    ],
    "1376a256": [
      36,
      24
    ],
    "63ac17f7": [
      36,
      24
    ],
    "c2672a4c": [
      36,
      24
    ],
    "36f6a7fc": [
      36,
      24
    ],
    "8d65400c": [
      36,
      24
    ],
    "33964b43": [
      36,
      24
    ],
    "6e266a2d": [
      36,
      24
    ],
    "8f302ac8": [
      36,
      24
    ],
    "3573e1be": [
      36,
      24
    ],
    "8fdb530e": [
      36,
      24
    ],
    "b983a238": [
      36,
      24
    ],
    "4b202446": [
      36,
      24
    ],
    "3e39b769": [
      36,
      24
    ],
    "7f202ba4": [
      36,
      24
    ],
    "c37b440a": [
      36,
      24
    ],
    "5bbb0598": [
      49
    ],
    "8976059e": [
      37
    ],
    "09731d94": [
      37
    ],
    "04da98c2": [
      2,
      33
    ],
    "edd6ec74": [
      37
    ],
    "6fc42588": [
      37
    ],
    "ef6bfc54": [
      23,
      41
    ],
    "63f70348": [
      5,
      60
    ],
    "a64c0b4c": [
      12,
      28
    ],
    "576ce557": [
      59,
      13
    ],
    "38478c94": [
      65,
      32
    ],
    "627bacf6": [
      39,
      68
    ],
    "09246e87": [
      39,
      68
    ],
    "0b15476e": [
      9,
      20
    ],
    "85dc7150": [
      57,
      54
    ],
    "ab115316": [
      38,
      64,
      75
    ],
    "51140baf": [
      38,
      64,
      75
    ],
    "235b72e0": [
      38,
      64,
      75
    ],
    "44ced7b3": [
      38,
      64,
      75
    ],
    "2bd72112": [
      38,
      64,
      75
    ],
    "e053de70": [
      38,
      64,
      75
    ],
    "36baa7de": [
      38,
      64,
      75
    ],
    "695235fa": [
      38,
      64,
      75
    ],
    "15e3b61e": [
      38,
      64,
      75
    ],
    "5cc944f1": [
      38,
      64,
      75
    ],
    "7f92a17e": [
      38,
      64,
      75
    ],
    "b512826c": [
      7,
      55
    ],
    "630ba029": [
      27,
      43
    ],
    "0cbad49c": [
      66,
      30
    ],
    "79cb28c5": [
      7,
      61
    ],
    "1532e69c": [
      7,
      10
    ],
    "b96e50f2": [
      35,
      44
    ],
    "ac3ccf7e": [
      29,
      46
    ],
    "35b36ea0": [
      50,
      14
    ],
    "1a0b8c60": [
      50,
      14
    ],
    "3edbf074": [
      50,
      14
    ],
    "2ea16354": [
      50,
      14
    ],
    "2b0b75d0": [
      50,
      14
    ],
    "3e563ecc": [
      19
    ],
    "4b23a45b": [
      51
    ],
    "a5311c4e": [
      6
    ],
    "3516cf66": [
      37
    ],
    "6e507550": [
      19
    ],
    "011be30c": [
      19
    ],
    "38aab8f5": [
      19
    ],
    "0aa1ed20": [
      2,
      33
    ],
    "050da144": [
      56,
      45
    ],
    "1f6a7242": [
      56,
      45
    ],
    "af1c4366": [
      37
    ],
    "4ec308a0": [
      49
    ],
    "1fbf8b02": [
      6
    ],
    "4a1c858a": [
      37
    ],
    "1952e34c": [
      56,
      45
    ],
    "a4608d98": [
      23,
      41
    ],
    "11c5243e": [
      5,
      60
    ],
    "1c81f138": [
      12,
      28
    ],
    "a4c8ca8e": [
      59,
      13
    ],
    "74d7fb0e": [
      31
    ],
    "58c0ecf3": [
      31
    ],
    "286f25d8": [
      65,
      32
    ],
    "27e4ae1a": [
      39,
      68
    ],
    "ff51552e": [
      39,
      68
    ],
    "8fbb9fb2": [
      9,
      20
    ],
    "3ad10294": [
      57,
      54
    ],
    "3294ce86": [
      38,
      64,
      75
    ],
    "d72ceb4a": [
      18,
      25
    ],
    "3de0a622": [
      18,
      25
    ],
    "5bbb0b53": [
      38,
      64,
      75
    ],
    "5f12a13d": [
      18,
      25
    ],
    "1d8f64c4": [
      18,
      25
    ],
    "7f83fde6": [
      38,
      64,
      75
    ],
    "165a4b3e": [
      38,
      64,
      75
    ],
    "37cdb011": [
      38,
      64,
      75
    ],
    "45d97056": [
      38,
      64,
      75
    ],
    "82ff6cb4": [
      38,
      64,
      75
    ],
    "b8d24980": [
      38,
      64,
      75
    ],
    "416b9b65": [
      38,
      64,
      75
    ],
    "3b4e42fd": [
      18,
      25
    ],
    "14eeb94f": [
      18,
      25
    ],
    "bbefb720": [
      38,
      64,
      75
    ],
    "0e0cf9cf": [
      38,
      64,
      75
    ],
    "0cb8c51f": [
      38,
      64,
      75
    ],
    "1c0e56b0": [
      7,
      55
    ],
    "e3156b2c": [
      47
    ],
    "692f6b54": [
      47
    ],
    "a9039dea": [
      47
    ],
    "13d95723": [
      47
    ],
    "eedd50f2": [
      27,
      43
    ],
    "f6586bd8": [
      66,
      30
    ],
    "204041b2": [
      7,
      61
    ],
    "bf37ca04": [
      7,
      10
    ],
    "548c8c65": [
      35,
      44
    ],
    "718519b7": [
      67
    ],
    "3343b577": [
      67
    ],
    "20c95cba": [
      29,
      46
    ],
    "1a4caa94": [
      50,
      14
    ],
    "31a85e8e": [
      50,
      14
    ],
    "274e502e": [
      50,
      14
    ],
    "14e61e24": [
      50,
      14
    ],
    "6c64f238": [
      50,
      14
    ],
    "61ad2bfa": [
      50,
      14
    ],
    "38d46de4": [
      19
    ],
    "35c994ae": [
      19
    ],
    "cbbcabf8": [
      19
    ],
    "e0bc1b6a": [
      19
    ],
    "60321eed": [
      19
    ],
    "aa47525a": [
      19
    ],
    "024cbc8b": [
      19
    ],
    "94f7afe4": [
      19
    ],
    "e42a2876": [
      4
    ],
    "6e562a1e": [
      63
    ],
    "1992ef02": [
      38,
      64,
      75
    ],
    "96e37164": [
      38,
      64,
      75
    ],
    "0866265c": [
      38,
      64,
      75
    ],
    "5fb45898": [
      38,
      64,
      75
    ],
    "616c4578": [
      38,
      64,
      75
    ],
    "04b91794": [
      38,
      64,
      75
    ],
    "174bc1b2": [
      38,
      64,
      75
    ],
    "7e59ef74": [
      38,
      64,
      75
    ],
    "36dc699e": [
      38,
      64,
      75
    ],
    "4458a101": [
      38,
      64,
      75
    ],
    "0d78ffa2": [
      38,
      64,
      75
    ],
    "5f0d62e0": [
      38,
      64,
      75
    ],
    "539e0544": [
      38,
      64,
      75
    ],
    "53fee74b": [
      38,
      64,
      75
    ],
    "2a3a9b48": [
      38,
      64,
      75
    ],
    "630a9f70": [
      38,
      64,
      75
    ],
    "959e5200": [
      38,
      64,
      75
    ],
    "2a757871": [
      38,
      64,
      75
    ],
    "d2e1513e": [
      38,
      64,
      75
    ],
    "03eb3be4": [
      38,
      64,
      75
    ],
    "11480fca": [
      38,
      64,
      75
    ],
    "1e5397d4": [
      38,
      64,
      75
    ],
    "0e027299": [
      38,
      64,
      75
    ],
    "67e18e43": [
      38,
      64,
      75
    ],
    "55bd332b": [
      38,
      64,
      75
    ],
    "1296f3ec": [
      38,
      64,
      75
    ],
    "1de99591": [
      38,
      64,
      75
    ],
    "57362eb0": [
      38,
      64,
      75
    ],
    "8daef83a": [
      38,
      64,
      75
    ],
    "64fe322e": [
      38,
      64,
      75
    ],
    "db874c02": [
      38,
      64,
      75
    ],
    "0801db2a": [
      38,
      64,
      75
    ],
    "0d704592": [
      38,
      64,
      75
    ],
    "3575efc0": [
      38,
      64,
      75
    ],
    "f678075e": [
      38,
      64,
      75
    ],
    "a8aa203e": [
      38,
      64,
      75
    ],
    "f06b0d18": [
      38,
      64,
      75
    ],
    "8b617b90": [
      38,
      64,
      75
    ],
    "55f76f49": [
      38,
      64,
      75
    ],
    "0247939b": [
      38,
      64,
      75
    ],
    "5a911986": [
      38,
      64,
      75
    ],
    "95ae03da": [
      38,
      64,
      75
    ],
    "690d3a4b": [
      38,
      64,
      75
    ],
    "719f6040": [
      38,
      64,
      75
    ],
    "27b0763b": [
      38,
      64,
      75
    ],
    "36ffa8c8": [
      38,
      64,
      75
    ],
    "59e009b6": [
      38,
      64,
      75
    ],
    "4ba27beb": [
      38,
      64,
      75
    ],
    "d88b1542": [
      38,
      64,
      75
    ],
    "33f61a5b": [
      38,
      64,
      75
    ],
    "ff501ff2": [
      38,
      64,
      75
    ],
    "09c63f39": [
      38,
      64,
      75
    ],
    "16adb715": [
      38,
      64,
      75
    ],
    "1bcd9106": [
      38,
      64,
      75
    ],
    "555e19f6": [
      38,
      64,
      75
    ],
    "391d6cc2": [
      38,
      64,
      75
    ],
    "caf72522": [
      38,
      64,
      75
    ],
    "2417e8de": [
      38,
      64,
      75
    ],
    "cbacdc56": [
      38,
      64,
      75
    ],
    "7300fdf5": [
      38,
      64,
      75
    ],
    "8d259176": [
      50,
      14
    ],
    "2c669336": [
      50,
      14
    ],
    "b0bca61e": [
      50,
      14
    ],
    "dd1b564a": [
      50,
      14
    ],
    "73013e8b": [
      50,
      14
    ],
    "c73ed79e": [
      50,
      14
    ],
    "6935e3d5": [
      50,
      14
    ],
    "521c6c6a": [
      50,
      14
    ],
    "67eccd7f": [
      50,
      14
    ],
    "99cdaafa": [
      50,
      14
    ],
    "620270d0": [
      50,
      14
    ],
    "839addbe": [
      50,
      14
    ],
    "1312dec9": [
      50,
      14
    ],
    "18b88329": [
      50,
      14
    ],
    "4724f3c6": [
      50,
      14
    ],
    "39a46a3b": [
      50,
      14
    ],
    "6e9fdac6": [
      50,
      14
    ],
    "121814d1": [
      50,
      14
    ],
    "a3db7f72": [
      50,
      14
    ],
    "07efa0da": [
      50,
      14
    ],
    "a530dca8": [
      50,
      14
    ],
    "53ea4623": [
      50,
      14
    ],
    "4b983f9c": [
      50,
      14
    ],
    "bf5a6926": [
      50,
      14
    ],
    "36c42c7c": [
      50,
      14
    ],
    "4b8474ba": [
      50,
      14
    ],
    "274e7876": [
      50,
      14
    ],
    "61d3e56e": [
      50,
      14
    ],
    "7501b334": [
      50,
      14
    ],
    "1b7e9293": [
      50,
      14
    ],
    "3c14a890": [
      50,
      14
    ],
    "03fe7086": [
      50,
      14
    ],
    "04cb800a": [
      9,
      20
    ],
    "2b93628c": [
      9,
      20
    ],
    "24b6d3ca": [
      9,
      20
    ],
    "2bc74454": [
      9,
      20
    ],
    "171f1cc3": [
      9,
      20
    ],
    "cd15f796": [
      9,
      20
    ],
    "1a6bd2f1": [
      9,
      20
    ],
    "649775ff": [
      9,
      20
    ],
    "0318d1d2": [
      9,
      20
    ],
    "0e6fb44d": [
      23,
      41
    ],
    "5a335b1b": [
      23,
      41
    ],
    "83d9bc32": [
      23,
      41
    ],
    "05596c65": [
      23,
      41
    ],
    "23b27a8d": [
      23,
      41
    ],
    "4456a552": [
      23,
      41
    ],
    "5347edd2": [
      23,
      41
    ],
    "29bc50dd": [
      23,
      41
    ],
    "1e6a5f9c": [
      23,
      41
    ],
    "0dc41503": [
      23,
      41
    ],
    "5d3bcdf8": [
      39,
      68
    ],
    "044271e0": [
      39,
      68
    ],
    "16bb825c": [
      39,
      68
    ],
    "39fd6bf4": [
      39,
      68
    ],
    "701417ec": [
      39,
      68
    ],
    "bae1a548": [
      39,
      68
    ],
    "6b7d8d62": [
      39,
      68
    ],
    "5583058c": [
      39,
      68
    ],
    "1e625276": [
      39,
      68
    ],
    "3b9e77d4": [
      39,
      68
    ],
    "3e70d9c8": [
      35,
      44
    ],
    "05d32448": [
      35,
      44
    ],
    "526c0c4c": [
      35,
      44
    ],
    "0cbcb426": [
      35,
      44
    ],
    "6f2da7f2": [
      35,
      44
    ],
    "6cb6bd94": [
      8
    ],
    "9692b27e": [
      8
    ],
    "89f9b444": [
      8
    ],
    "7fd9188b": [
      8
    ],
    "c1ea2bf8": [
      8
    ],
    "0151ea8a": [
      62
    ],
    "99e978b2": [
      62
    ],
    "622c37fb": [
      62
    ],
    "df631ec6": [
      62
    ],
    "24af51d6": [
      62
    ],
    "0b631e4e": [
      7,
      10
    ],
    "f8ab231a": [
      7,
      10
    ],
    "1cd635e9": [
      7,
      10
    ],
    "53368ff7": [
      7,
      10
    ],
    "601b9670": [
      69,
      16
    ],
    "f387736c": [
      69,
      16
    ],
    "9b8ff364": [
      69,
      16
    ],
    "1f680dc0": [
      69,
      16
    ],
    "4f28c6e8": [
      69,
      16
    ],
    "69f51b7a": [
      2,
      33
    ],
    "15c1643a": [
      2,
      33
    ],
    "2e258bf1": [
      2,
      33
    ],
    "55f8b504": [
      2,
      33
    ],
    "9c744dd2": [
      2,
      33
    ],
    "d1dab5f8": [
      69,
      58
    ],
    "1cb741b1": [
      69,
      58
    ],
    "025ea152": [
      69,
      58
    ],
    "1a0f03a7": [
      69,
      58
    ],
    "2621a36c": [
      69,
      58
    ],
    "334af64a": [
      11
    ],
    "22c05903": [
      11
    ],
    "d679d54e": [
      11
    ],
    "c6b18066": [
      11
    ],
    "0feedc7f": [
      11
    ],
    "6a1396f0": [
      69,
      53
    ],
    "22d770e5": [
      69,
      53
    ],
    "3d58ce4e": [
      69,
      53
    ],
    "202f32db": [
      69,
      53
    ],
    "611bd068": [
      69,
      53
    ],
    "0a04cf6f": [
      56,
      45
    ],
    "83f31080": [
      56,
      45
    ],
    "2ff7cd76": [
      56,
      45
    ],
    "37ed5e8a": [
      56,
      45
    ],
    "632fe06b": [
      56,
      45
    ],
    "7ca6d5dc": [
      3
    ],
    "257279b1": [
      3
    ],
    "c2207bf0": [
      3
    ],
    "9e22ce6a": [
      3
    ],
    "fa8ea97c": [
      7,
      61
    ],
    "63ef6b77": [
      7,
      61
    ],
    "0c0c4e14": [
      7,
      61
    ],
    "eb05ee26": [
      7,
      61
    ],
    "726c48ae": [
      7,
      61
    ],
    "d7e141ce": [
      5,
      60
    ],
    "80077da0": [
      5,
      60
    ],
    "8501cc46": [
      5,
      60
    ],
    "0bcad5f7": [
      5,
      60
    ],
    "5148d06a": [
      27,
      43
    ],
    "19e95f77": [
      27,
      43
    ],
    "cb728dac": [
      27,
      43
    ],
    "35e85d7e": [
      27,
      43
    ],
    "7e4e7d50": [
      27,
      43
    ],
    "247a7f5b": [
      12,
      28
    ],
    "2b58c7a1": [
      12,
      28
    ],
    "4a158319": [
      12,
      28
    ],
    "71bdb82a": [
      12,
      28
    ],
    "ad27ce82": [
      12,
      28
    ],
    "06449d54": [
      59,
      13
    ],
    "811bb87c": [
      59,
      13
    ],
    "dc38a296": [
      59,
      13
    ],
    "ac817d48": [
      59,
      13
    ],
    "f32399e4": [
      15
    ],
    "96e93f54": [
      15
    ],
    "69ccd706": [
      15
    ],
    "7fadd220": [
      15
    ],
    "4dd49b2c": [
      15
    ],
    "7d5bbd92": [
      65,
      32
    ],
    "4aff96a0": [
      65,
      32
    ],
    "b7861206": [
      65,
      32
    ],
    "e57a472c": [
      65,
      32
    ],
    "6aadc723": [
      65,
      32
    ],
    "4654b0cb": [
      7,
      55
    ],
    "0af1d348": [
      7,
      55
    ],
    "45788f29": [
      7,
      55
    ],
    "93d036dc": [
      7,
      55
    ],
    "a9d03062": [
      7,
      55
    ],
    "64d88908": [
      48
    ],
    "4267a934": [
      48
    ],
    "c62d17cc": [
      48
    ],
    "361cc248": [
      48
    ],
    "b6daae98": [
      48
    ],
    "fb47194e": [
      57,
      54
    ],
    "337fc6de": [
      57,
      54
    ],
    "15dc1dca": [
      57,
      54
    ],
    "02bb8eb0": [
      57,
      54
    ],
    "4dcc957e": [
      57,
      54
    ],
    "42f6570d": [
      52
    ],
    "5a57e4c0": [
      52
    ],
    "61d94232": [
      52
    ],
    "dbfc2d2c": [
      52
    ],
    "7c46ade6": [
      52
    ],
    "497782e0": [
      21
    ],
    "c5b01de4": [
      21
    ],
    "0e860fb4": [
      21
    ],
    "0fad625a": [
      21
    ],
    "6766ed2c": [
      29,
      46
    ],
    "4eeda798": [
      29,
      46
    ],
    "0f0c8ba2": [
      29,
      46
    ],
    "1a4d3932": [
      29,
      46
    ],
    "5dd2c56f": [
      66,
      30
    ],
    "1c73282e": [
      66,
      30
    ],
    "1842a0f2": [
      66,
      30
    ],
    "ea1b9942": [
      66,
      30
    ],
    "de611fbe": [
      66,
      30
    ],
    "0f3aa19c": [
      42
    ],
    "7c60239a": [
      42
    ],
    "70153cae": [
      42
    ],
    "2dcf5a38": [
      36,
      24
    ],
    "2f45f32b": [
      36,
      24
    ],
    "38877fc9": [
      36,
      24
    ],
    "0a943846": [
      22,
      34,
      73,
      74,
      72,
      70,
      71
    ],
    "26ad07f5": [
      22,
      34,
      73,
      74,
      72,
      70,
      71
    ],
    "5ffca87c": [
      36,
      24
    ],
    "1bfb384c": [
      36,
      24
    ],
    "5e524a4c": [
      36,
      24
    ],
    "7941add0": [
      22,
      34,
      73,
      74,
      72,
      70,
      71
    ],
    "d30ded72": [
      22,
      34,
      73,
      74,
      72,
      70,
      71
    ],
    "12fa1f25": [
      5,
      60
    ],
    "de488e1e": [
      12,
      28
    ],
    "357d77e0": [
      59,
      13
    ],
    "70f34fce": [
      2,
      33
    ],
    "3ebd4545": [
      56,
      45
    ],
    "a1db466c": [
      29,
      46
    ],
    "6a021d1e": [
      35,
      44
    ],
    "1993dbd0": [
      39,
      68
    ],
    "2bf986e6": [
      65,
      32
    ],
    "12e70560": [
      9,
      20
    ],
    "b0c387a2": [
      57,
      54
    ],
    "3c5560e1": [
      7,
      55
    ],
    "4d981500": [
      27,
      43
    ],
    "60a4bbbb": [
      66,
      30
    ],
    "2c1467ce": [
      7,
      61
    ],
    "7c350ca5": [
      7,
      10
    ],
    "0a2c9b3e": [
      50,
      14
    ],
    "71309c0c": [
      38,
      64,
      75
    ],
    "23828a88": [
      38,
      64,
      75
    ],
    "7c04eac7": [
      50,
      14
    ],
    "72d676ad": [
      23,
      41
    ],
    "14b581e3": [
      18,
      25
    ],
    "6faf69ba": [
      38,
      64,
      75
    ],
    "4e924786": [
      38,
      64,
      75
    ],
    "7da0240c": [
      38,
      64,
      75
    ],
    "d07fd3c2": [
      50,
      14
    ],
    "4cb8b227": [
      50,
      14
    ],
    "3a50801d": [
      50,
      14
    ],
    "77d7090a": [
      38,
      64,
      75
    ],
    "64b8a167": [
      38,
      64,
      75
    ],
    "2197485f": [
      38,
      64,
      75
    ],
    "5663a437": [
      38,
      64,
      75
    ],
    "1d1ca0ce": [
      38,
      64,
      75
    ]
  },
  "assetsMapping": {
    "01ef1929339ced88b360.js": "32c3a158",
    "068e31b9cfb2a1f323c7.js": "bba68bf6",
    "09fcce816da279344f0f.js": "053532da",
    "147a7fa5f3d1d2aa630b.js": "00d355d3",
    "1dfd7eba873dea5d2099.js": "2f02b5a8",
    "26e3844b218c0b5e2e5f.js": "87259310",
    "2cf8177f2bc0cc0607d8.js": "55ab96b2",
    "361904d513e233a610ec.js": "1a0ab5d0",
    "367c3ec980f82a4a0703.js": "47c0d8aa",
    "3757f229453f330a74ee.js": "0e708eca",
    "38082ef60047c29d57cd.js": "6fca0322",
    "48a2df7cea1b8422d699.js": "bba68bf6",
    "49119de98847fb151006.js": "0f680f67",
    "49e762b335e6e483107b.js": "4924633d",
    "63fd95d42884f282086f.js": "7ea1d828",
    "6c93c987ff832d5d8921.js": "3f3a307c",
    "6f6bfe4dc68f4249ef0c.js": "0859c165",
    "772da461fb9d6e5b0200.js": "1be697b8",
    "7a2e040ed89501ffa278.js": "9d3e967c",
    "837e5ccff1f84dc31e5c.js": "5ab90a77",
    "85e1ca3911df2e9d11c9.js": "ad17ef58",
    "874327057dbddee5787d.js": "b2d8c640",
    "8e95980befef01b638d9.js": "1a3ae26b",
    "9c5d8c305eae84115714.js": "06499250",
    "a338aaa5d928f106b53a.js": "17c5182a",
    "af26153217755f751c5c.js": "0fc22e05",
    "afe15297bc91c3978485.js": "489181f2",
    "b13f2114018486ce6b61.js": "9ba714b6",
    "b79aa88aa31875cd5650.js": "1e6beb0c",
    "bb062fa75d7c1914a441.js": "2a130dde",
    "bb76858497b8401d8c1e.js": "841cc9ac",
    "c14f6a5fba3cc7c8ec95.js": "37ae2162",
    "c69c67e5939fec6248d5.js": "b6544d4a",
    "ccacb95a7a151e2a5eb1.js": "0c033ee4",
    "cf4bb06780e032e74477.js": "049cd7ac",
    "d00a54dd7f722d1efa47.js": "58d3a99b",
    "d0aebe7d6fb1619b2b80.js": "0037b176",
    "d0f3232ef7fd36707b2a.js": "5a2803a8",
    "e1432ec96fd88320a590.js": "58d3b817",
    "e461e4e64a928cf0eadd.js": "2112c0a8",
    "e6e6152e56c550d24498.js": "6cc1d1d6",
    "e792f7b476c091f672dd.js": "94a3c264",
    "e94f3b72cdd433482cce.js": "bba68bf6",
    "ee9ee360b140ce490d48.js": "1cb3f55f",
    "f428cd859141d5ae8175.js": "7e1e61ce",
    "f43df91d429ecf845bb5.js": "d8c1d6d2"
  }
}